valueplayerwidget/__init__.py
valueplayerwidget/timer.py
valueplayerwidget/value_player_widget.py
valueplayerwidget-0.1.4.dist-info/LICENSE
valueplayerwidget-0.1.4.dist-info/LICENSE.txt
valueplayerwidget-0.1.4.dist-info/METADATA
valueplayerwidget-0.1.4.dist-info/WHEEL
valueplayerwidget-0.1.4.dist-info/top_level.txt
valueplayerwidget-0.1.4.dist-info/RECORD
