Metadata-Version: 2.1
Name: valueplayerwidget
Version: 0.1.4
Summary: A Player for Widgets with Values with Jupyter Notebook
Home-page: https://gitlab.u-psud.fr/edwige.gros/ValuePlayerWidget.git
Author: Edwige Gros
Author-email: edwige.gros@laposte.net
License: UNKNOWN
Platform: UNKNOWN
Classifier: Programming Language :: Python :: 3
Classifier: License :: OSI Approved :: MIT License
Classifier: Operating System :: OS Independent
Requires-Python: >=3.6
Requires-Dist: timer
Requires-Dist: ipywidgets
Requires-Dist: delpywidget
